register_it/__init__.py
register_it/register_it.py
register_it/utils.py
register_it-0.3.dist-info/LICENSE
register_it-0.3.dist-info/METADATA
register_it-0.3.dist-info/WHEEL
register_it-0.3.dist-info/top_level.txt
register_it-0.3.dist-info/RECORD
