Metadata-Version: 2.1
Name: register-it
Version: 0.3
Summary: Register it: A more flexible register for the DeepLearning project.
Home-page: https://github.com/lartpang/RegisterIt
Author: lartpang
Author-email: lartpang@gmail.com
License: MIT
Keywords: tools,deep learning
Platform: UNKNOWN
Classifier: Development Status :: 5 - Production/Stable
Classifier: Environment :: Console
Classifier: Intended Audience :: Developers
Classifier: License :: OSI Approved :: MIT License
Classifier: Operating System :: OS Independent
Classifier: Programming Language :: Python :: 3.7
Classifier: Programming Language :: Python :: 3.8
Classifier: Programming Language :: Python :: 3.9
Classifier: Topic :: Scientific/Engineering :: Artificial Intelligence
License-File: LICENSE
